[{"id":1, "quest_group_id":346, "quest_module_id":1009, "weight":1},
 {"id":2, "quest_group_id":346, "quest_module_id":1010, "weight":2},
 {"id":3, "quest_group_id":346, "quest_module_id":1011, "weight":3},
 {"id":7, "quest_group_id":347, "quest_module_id":1015, "weight":7},
 {"id":8, "quest_group_id":347, "quest_module_id":1016, "weight":8},
 {"id":9, "quest_group_id":347, "quest_module_id":1017, "weight":9},
 {"id":10, "quest_group_id":347, "quest_module_id":1018, "weight":10},
 {"id":11, "quest_group_id":347, "quest_module_id":1019, "weight":11},
 {"id":12, "quest_group_id":347, "quest_module_id":1020, "weight":12},
 {"id":13, "quest_group_id":347, "quest_module_id":1021, "weight":13},
 {"id":14, "quest_group_id":347, "quest_module_id":1022, "weight":14},
 {"id":15, "quest_group_id":348, "quest_module_id":1023, "weight":15},
 {"id":16, "quest_group_id":348, "quest_module_id":1024, "weight":16},
 {"id":17, "quest_group_id":348, "quest_module_id":1025, "weight":17},
 {"id":18, "quest_group_id":348, "quest_module_id":1026, "weight":18},
 {"id":19, "quest_group_id":348, "quest_module_id":1027, "weight":19},
 {"id":20, "quest_group_id":348, "quest_module_id":1028, "weight":20},
 {"id":21, "quest_group_id":348, "quest_module_id":1029, "weight":21},
 {"id":22, "quest_group_id":348, "quest_module_id":1030, "weight":22},
 {"id":23, "quest_group_id":348, "quest_module_id":1031, "weight":23},
 {"id":24, "quest_group_id":348, "quest_module_id":1032, "weight":24},
 {"id":25, "quest_group_id":348, "quest_module_id":1033, "weight":25},
 {"id":26, "quest_group_id":348, "quest_module_id":1034, "weight":26},
 {"id":27, "quest_group_id":348, "quest_module_id":1035, "weight":27},
 {"id":28, "quest_group_id":348, "quest_module_id":1036, "weight":28},
 {"id":29, "quest_group_id":348, "quest_module_id":1037, "weight":29},
 {"id":30, "quest_group_id":350, "quest_module_id":1038, "weight":30},
 {"id":31, "quest_group_id":350, "quest_module_id":1039, "weight":31},
 {"id":32, "quest_group_id":350, "quest_module_id":1040, "weight":32},
 {"id":33, "quest_group_id":350, "quest_module_id":1041, "weight":33},
 {"id":34, "quest_group_id":350, "quest_module_id":1042, "weight":34},
 {"id":35, "quest_group_id":350, "quest_module_id":1043, "weight":35},
 {"id":36, "quest_group_id":351, "quest_module_id":1044, "weight":36},
 {"id":37, "quest_group_id":351, "quest_module_id":1045, "weight":37},
 {"id":38, "quest_group_id":351, "quest_module_id":1046, "weight":38},
 {"id":39, "quest_group_id":351, "quest_module_id":1047, "weight":39},
 {"id":40, "quest_group_id":351, "quest_module_id":1048, "weight":40},
 {"id":41, "quest_group_id":351, "quest_module_id":1049, "weight":41},
 {"id":42, "quest_group_id":351, "quest_module_id":1050, "weight":42},
 {"id":43, "quest_group_id":351, "quest_module_id":1051, "weight":43},
 {"id":44, "quest_group_id":351, "quest_module_id":1052, "weight":44},
 {"id":45, "quest_group_id":351, "quest_module_id":1053, "weight":45},
 {"id":46, "quest_group_id":351, "quest_module_id":1054, "weight":46},
 {"id":47, "quest_group_id":352, "quest_module_id":1055, "weight":47},
 {"id":48, "quest_group_id":352, "quest_module_id":1056, "weight":48},
 {"id":49, "quest_group_id":352, "quest_module_id":1057, "weight":49},
 {"id":50, "quest_group_id":352, "quest_module_id":1058, "weight":50},
 {"id":51, "quest_group_id":352, "quest_module_id":1059, "weight":51},
 {"id":52, "quest_group_id":352, "quest_module_id":1060, "weight":52},
 {"id":53, "quest_group_id":352, "quest_module_id":1061, "weight":53},
 {"id":54, "quest_group_id":352, "quest_module_id":1062, "weight":54},
 {"id":55, "quest_group_id":352, "quest_module_id":1063, "weight":55},
 {"id":56, "quest_group_id":353, "quest_module_id":1064, "weight":2},
 {"id":57, "quest_group_id":353, "quest_module_id":1065, "weight":3},
 {"id":58, "quest_group_id":353, "quest_module_id":1066, "weight":4},
 {"id":59, "quest_group_id":353, "quest_module_id":1067, "weight":1},
 {"id":60, "quest_group_id":353, "quest_module_id":1068, "weight":5},
 {"id":61, "quest_group_id":353, "quest_module_id":1069, "weight":6},
 {"id":62, "quest_group_id":353, "quest_module_id":1070, "weight":7},
 {"id":63, "quest_group_id":355, "quest_module_id":1071, "weight":63},
 {"id":64, "quest_group_id":355, "quest_module_id":1072, "weight":64},
 {"id":65, "quest_group_id":355, "quest_module_id":1073, "weight":65},
 {"id":66, "quest_group_id":356, "quest_module_id":1074, "weight":1},
 {"id":67, "quest_group_id":372, "quest_module_id":1075, "weight":67},
 {"id":68, "quest_group_id":372, "quest_module_id":1076, "weight":68},
 {"id":69, "quest_group_id":372, "quest_module_id":1077, "weight":69},
 {"id":70, "quest_group_id":372, "quest_module_id":1078, "weight":70},
 {"id":71, "quest_group_id":373, "quest_module_id":1079, "weight":71},
 {"id":72, "quest_group_id":373, "quest_module_id":1080, "weight":72},
 {"id":73, "quest_group_id":373, "quest_module_id":1081, "weight":73},
 {"id":74, "quest_group_id":373, "quest_module_id":1082, "weight":74},
 {"id":75, "quest_group_id":373, "quest_module_id":1083, "weight":75},
 {"id":76, "quest_group_id":373, "quest_module_id":1084, "weight":76},
 {"id":77, "quest_group_id":374, "quest_module_id":1085, "weight":77},
 {"id":78, "quest_group_id":374, "quest_module_id":1086, "weight":78},
 {"id":79, "quest_group_id":374, "quest_module_id":1087, "weight":79},
 {"id":80, "quest_group_id":374, "quest_module_id":1088, "weight":80},
 {"id":81, "quest_group_id":374, "quest_module_id":1089, "weight":81},
 {"id":82, "quest_group_id":374, "quest_module_id":1090, "weight":82},
 {"id":83, "quest_group_id":375, "quest_module_id":1091, "weight":83},
 {"id":84, "quest_group_id":375, "quest_module_id":1092, "weight":84},
 {"id":85, "quest_group_id":375, "quest_module_id":1093, "weight":85},
 {"id":86, "quest_group_id":375, "quest_module_id":1094, "weight":86},
 {"id":87, "quest_group_id":375, "quest_module_id":1095, "weight":87},
 {"id":88, "quest_group_id":376, "quest_module_id":1096, "weight":88},
 {"id":89, "quest_group_id":376, "quest_module_id":1097, "weight":89},
 {"id":90, "quest_group_id":376, "quest_module_id":1098, "weight":90},
 {"id":91, "quest_group_id":376, "quest_module_id":1099, "weight":91},
 {"id":92, "quest_group_id":377, "quest_module_id":1100, "weight":92},
 {"id":93, "quest_group_id":377, "quest_module_id":1101, "weight":93},
 {"id":94, "quest_group_id":377, "quest_module_id":1102, "weight":94},
 {"id":95, "quest_group_id":377, "quest_module_id":1103, "weight":95},
 {"id":96, "quest_group_id":377, "quest_module_id":1104, "weight":96},
 {"id":97, "quest_group_id":379, "quest_module_id":1105, "weight":97},
 {"id":98, "quest_group_id":379, "quest_module_id":1106, "weight":98},
 {"id":99, "quest_group_id":379, "quest_module_id":1107, "weight":99},
 {"id":100, "quest_group_id":379, "quest_module_id":1108, "weight":100},
 {"id":101, "quest_group_id":380, "quest_module_id":1109, "weight":101},
 {"id":102, "quest_group_id":380, "quest_module_id":1110, "weight":102},
 {"id":103, "quest_group_id":380, "quest_module_id":1111, "weight":103},
 {"id":104, "quest_group_id":380, "quest_module_id":1112, "weight":104},
 {"id":105, "quest_group_id":380, "quest_module_id":1113, "weight":105},
 {"id":106, "quest_group_id":380, "quest_module_id":1114, "weight":106},
 {"id":107, "quest_group_id":381, "quest_module_id":1115, "weight":1},
 {"id":108, "quest_group_id":381, "quest_module_id":1116, "weight":2},
 {"id":109, "quest_group_id":381, "quest_module_id":1117, "weight":3},
 {"id":110, "quest_group_id":381, "quest_module_id":1118, "weight":4},
 {"id":111, "quest_group_id":381, "quest_module_id":1119, "weight":5},
 {"id":112, "quest_group_id":381, "quest_module_id":1120, "weight":6},
 {"id":113, "quest_group_id":381, "quest_module_id":1121, "weight":7},
 {"id":114, "quest_group_id":381, "quest_module_id":1122, "weight":10},
 {"id":115, "quest_group_id":381, "quest_module_id":1123, "weight":11},
 {"id":116, "quest_group_id":381, "quest_module_id":1124, "weight":8},
 {"id":117, "quest_group_id":381, "quest_module_id":1125, "weight":9},
 {"id":118, "quest_group_id":382, "quest_module_id":1126, "weight":118},
 {"id":119, "quest_group_id":382, "quest_module_id":1127, "weight":119},
 {"id":120, "quest_group_id":382, "quest_module_id":1128, "weight":120},
 {"id":121, "quest_group_id":382, "quest_module_id":1129, "weight":121},
 {"id":122, "quest_group_id":382, "quest_module_id":1130, "weight":122},
 {"id":123, "quest_group_id":382, "quest_module_id":1131, "weight":123},
 {"id":124, "quest_group_id":382, "quest_module_id":1132, "weight":124},
 {"id":125, "quest_group_id":382, "quest_module_id":1133, "weight":125},
 {"id":126, "quest_group_id":382, "quest_module_id":1134, "weight":126},
 {"id":127, "quest_group_id":382, "quest_module_id":1135, "weight":127},
 {"id":128, "quest_group_id":382, "quest_module_id":1136, "weight":128},
 {"id":129, "quest_group_id":382, "quest_module_id":1137, "weight":129},
 {"id":130, "quest_group_id":382, "quest_module_id":1138, "weight":130},
 {"id":131, "quest_group_id":382, "quest_module_id":1139, "weight":131},
 {"id":132, "quest_group_id":383, "quest_module_id":1140, "weight":132},
 {"id":133, "quest_group_id":384, "quest_module_id":1141, "weight":133},
 {"id":134, "quest_group_id":384, "quest_module_id":1142, "weight":134},
 {"id":135, "quest_group_id":384, "quest_module_id":1143, "weight":135},
 {"id":136, "quest_group_id":384, "quest_module_id":1144, "weight":136},
 {"id":137, "quest_group_id":384, "quest_module_id":1145, "weight":137},
 {"id":138, "quest_group_id":384, "quest_module_id":1146, "weight":138},
 {"id":139, "quest_group_id":384, "quest_module_id":1147, "weight":139},
 {"id":140, "quest_group_id":384, "quest_module_id":1148, "weight":140},
 {"id":141, "quest_group_id":385, "quest_module_id":1149, "weight":1},
 {"id":142, "quest_group_id":385, "quest_module_id":1150, "weight":2},
 {"id":143, "quest_group_id":385, "quest_module_id":1151, "weight":3},
 {"id":144, "quest_group_id":385, "quest_module_id":1152, "weight":5},
 {"id":145, "quest_group_id":385, "quest_module_id":1153, "weight":4},
 {"id":146, "quest_group_id":385, "quest_module_id":1154, "weight":6},
 {"id":147, "quest_group_id":386, "quest_module_id":1155, "weight":5},
 {"id":148, "quest_group_id":386, "quest_module_id":1156, "weight":1},
 {"id":149, "quest_group_id":386, "quest_module_id":1157, "weight":2},
 {"id":150, "quest_group_id":386, "quest_module_id":1158, "weight":3},
 {"id":151, "quest_group_id":386, "quest_module_id":1159, "weight":4},
 {"id":152, "quest_group_id":387, "quest_module_id":1160, "weight":152},
 {"id":153, "quest_group_id":387, "quest_module_id":1161, "weight":153},
 {"id":154, "quest_group_id":387, "quest_module_id":1162, "weight":154},
 {"id":155, "quest_group_id":387, "quest_module_id":1163, "weight":155},
 {"id":156, "quest_group_id":387, "quest_module_id":1164, "weight":156},
 {"id":157, "quest_group_id":387, "quest_module_id":1165, "weight":157},
 {"id":158, "quest_group_id":387, "quest_module_id":1166, "weight":158},
 {"id":159, "quest_group_id":387, "quest_module_id":1167, "weight":159},
 {"id":160, "quest_group_id":387, "quest_module_id":1168, "weight":160},
 {"id":161, "quest_group_id":387, "quest_module_id":1169, "weight":161},
 {"id":162, "quest_group_id":387, "quest_module_id":1170, "weight":162},
 {"id":169, "quest_group_id":387, "quest_module_id":1177, "weight":169},
 {"id":170, "quest_group_id":387, "quest_module_id":1178, "weight":170},
 {"id":171, "quest_group_id":388, "quest_module_id":1179, "weight":4},
 {"id":172, "quest_group_id":388, "quest_module_id":1180, "weight":1},
 {"id":173, "quest_group_id":388, "quest_module_id":1181, "weight":2},
 {"id":174, "quest_group_id":388, "quest_module_id":1182, "weight":3},
 {"id":175, "quest_group_id":389, "quest_module_id":1183, "weight":1},
 {"id":176, "quest_group_id":390, "quest_module_id":1184, "weight":176},
 {"id":177, "quest_group_id":390, "quest_module_id":1185, "weight":177},
 {"id":178, "quest_group_id":390, "quest_module_id":1186, "weight":178},
 {"id":179, "quest_group_id":392, "quest_module_id":1187, "weight":179},
 {"id":180, "quest_group_id":392, "quest_module_id":1188, "weight":180},
 {"id":181, "quest_group_id":392, "quest_module_id":1189, "weight":181},
 {"id":182, "quest_group_id":392, "quest_module_id":1190, "weight":182},
 {"id":183, "quest_group_id":393, "quest_module_id":1191, "weight":183},
 {"id":184, "quest_group_id":393, "quest_module_id":1192, "weight":184},
 {"id":185, "quest_group_id":393, "quest_module_id":1193, "weight":185},
 {"id":186, "quest_group_id":393, "quest_module_id":1194, "weight":186},
 {"id":187, "quest_group_id":393, "quest_module_id":1195, "weight":187},
 {"id":188, "quest_group_id":395, "quest_module_id":1196, "weight":188},
 {"id":189, "quest_group_id":395, "quest_module_id":1197, "weight":189},
 {"id":190, "quest_group_id":395, "quest_module_id":1198, "weight":190},
 {"id":191, "quest_group_id":395, "quest_module_id":1199, "weight":191},
 {"id":192, "quest_group_id":395, "quest_module_id":1200, "weight":192},
 {"id":193, "quest_group_id":395, "quest_module_id":1201, "weight":193},
 {"id":194, "quest_group_id":395, "quest_module_id":1202, "weight":194},
 {"id":195, "quest_group_id":395, "quest_module_id":1203, "weight":195},
 {"id":196, "quest_group_id":395, "quest_module_id":1204, "weight":196},
 {"id":197, "quest_group_id":395, "quest_module_id":1205, "weight":197},
 {"id":198, "quest_group_id":395, "quest_module_id":1206, "weight":198},
 {"id":199, "quest_group_id":395, "quest_module_id":1207, "weight":199},
 {"id":200, "quest_group_id":396, "quest_module_id":1208, "weight":200},
 {"id":201, "quest_group_id":396, "quest_module_id":1209, "weight":201},
 {"id":202, "quest_group_id":396, "quest_module_id":1210, "weight":202},
 {"id":203, "quest_group_id":396, "quest_module_id":1211, "weight":203},
 {"id":204, "quest_group_id":396, "quest_module_id":1212, "weight":204},
 {"id":205, "quest_group_id":396, "quest_module_id":1213, "weight":205},
 {"id":206, "quest_group_id":396, "quest_module_id":1214, "weight":206},
 {"id":207, "quest_group_id":396, "quest_module_id":1215, "weight":207},
 {"id":208, "quest_group_id":396, "quest_module_id":1216, "weight":208},
 {"id":209, "quest_group_id":396, "quest_module_id":1217, "weight":209},
 {"id":210, "quest_group_id":396, "quest_module_id":1218, "weight":210},
 {"id":211, "quest_group_id":396, "quest_module_id":1219, "weight":211},
 {"id":212, "quest_group_id":396, "quest_module_id":1220, "weight":212},
 {"id":213, "quest_group_id":396, "quest_module_id":1221, "weight":213},
 {"id":214, "quest_group_id":396, "quest_module_id":1222, "weight":214},
 {"id":215, "quest_group_id":396, "quest_module_id":1223, "weight":215},
 {"id":216, "quest_group_id":396, "quest_module_id":1224, "weight":216},
 {"id":217, "quest_group_id":396, "quest_module_id":1225, "weight":217},
 {"id":218, "quest_group_id":396, "quest_module_id":1226, "weight":218},
 {"id":219, "quest_group_id":397, "quest_module_id":1227, "weight":219},
 {"id":220, "quest_group_id":397, "quest_module_id":1228, "weight":220},
 {"id":221, "quest_group_id":397, "quest_module_id":1229, "weight":221},
 {"id":222, "quest_group_id":397, "quest_module_id":1230, "weight":222},
 {"id":223, "quest_group_id":397, "quest_module_id":1231, "weight":223},
 {"id":224, "quest_group_id":397, "quest_module_id":1232, "weight":224},
 {"id":225, "quest_group_id":397, "quest_module_id":1233, "weight":225},
 {"id":226, "quest_group_id":397, "quest_module_id":1234, "weight":226},
 {"id":227, "quest_group_id":397, "quest_module_id":1235, "weight":227},
 {"id":228, "quest_group_id":397, "quest_module_id":1236, "weight":228},
 {"id":229, "quest_group_id":397, "quest_module_id":1237, "weight":229},
 {"id":230, "quest_group_id":398, "quest_module_id":1238, "weight":230},
 {"id":231, "quest_group_id":398, "quest_module_id":1239, "weight":231},
 {"id":232, "quest_group_id":398, "quest_module_id":1240, "weight":232},
 {"id":233, "quest_group_id":398, "quest_module_id":1241, "weight":233},
 {"id":234, "quest_group_id":398, "quest_module_id":1242, "weight":234},
 {"id":235, "quest_group_id":398, "quest_module_id":1243, "weight":235},
 {"id":236, "quest_group_id":398, "quest_module_id":1244, "weight":236},
 {"id":237, "quest_group_id":398, "quest_module_id":1245, "weight":237},
 {"id":238, "quest_group_id":399, "quest_module_id":1246, "weight":238},
 {"id":239, "quest_group_id":399, "quest_module_id":1247, "weight":239},
 {"id":240, "quest_group_id":401, "quest_module_id":1248, "weight":240},
 {"id":241, "quest_group_id":401, "quest_module_id":1249, "weight":241},
 {"id":242, "quest_group_id":401, "quest_module_id":1250, "weight":242},
 {"id":243, "quest_group_id":401, "quest_module_id":1251, "weight":243},
 {"id":244, "quest_group_id":401, "quest_module_id":1252, "weight":244},
 {"id":245, "quest_group_id":401, "quest_module_id":1253, "weight":245},
 {"id":246, "quest_group_id":401, "quest_module_id":1254, "weight":246},
 {"id":247, "quest_group_id":401, "quest_module_id":1255, "weight":247},
 {"id":248, "quest_group_id":401, "quest_module_id":1256, "weight":248},
 {"id":249, "quest_group_id":401, "quest_module_id":1257, "weight":249},
 {"id":250, "quest_group_id":401, "quest_module_id":1258, "weight":250},
 {"id":251, "quest_group_id":402, "quest_module_id":1259, "weight":251},
 {"id":252, "quest_group_id":402, "quest_module_id":1260, "weight":252},
 {"id":253, "quest_group_id":402, "quest_module_id":1261, "weight":253},
 {"id":254, "quest_group_id":402, "quest_module_id":1262, "weight":254},
 {"id":255, "quest_group_id":402, "quest_module_id":1263, "weight":255},
 {"id":256, "quest_group_id":402, "quest_module_id":1264, "weight":256},
 {"id":257, "quest_group_id":402, "quest_module_id":1265, "weight":257},
 {"id":258, "quest_group_id":402, "quest_module_id":1266, "weight":258},
 {"id":259, "quest_group_id":402, "quest_module_id":1267, "weight":259},
 {"id":260, "quest_group_id":402, "quest_module_id":1268, "weight":260},
 {"id":261, "quest_group_id":402, "quest_module_id":1269, "weight":261},
 {"id":262, "quest_group_id":402, "quest_module_id":1270, "weight":262},
 {"id":263, "quest_group_id":402, "quest_module_id":1271, "weight":263},
 {"id":264, "quest_group_id":402, "quest_module_id":1272, "weight":264},
 {"id":265, "quest_group_id":402, "quest_module_id":1273, "weight":265},
 {"id":266, "quest_group_id":402, "quest_module_id":1274, "weight":266},
 {"id":267, "quest_group_id":402, "quest_module_id":1275, "weight":267},
 {"id":268, "quest_group_id":402, "quest_module_id":1276, "weight":268},
 {"id":269, "quest_group_id":402, "quest_module_id":1277, "weight":269},
 {"id":270, "quest_group_id":403, "quest_module_id":1278, "weight":270},
 {"id":271, "quest_group_id":403, "quest_module_id":1279, "weight":271},
 {"id":272, "quest_group_id":403, "quest_module_id":1280, "weight":272},
 {"id":273, "quest_group_id":403, "quest_module_id":1281, "weight":273},
 {"id":274, "quest_group_id":403, "quest_module_id":1282, "weight":274},
 {"id":275, "quest_group_id":403, "quest_module_id":1283, "weight":275},
 {"id":276, "quest_group_id":403, "quest_module_id":1284, "weight":276},
 {"id":277, "quest_group_id":403, "quest_module_id":1285, "weight":277},
 {"id":278, "quest_group_id":403, "quest_module_id":1286, "weight":278},
 {"id":279, "quest_group_id":403, "quest_module_id":1287, "weight":279},
 {"id":280, "quest_group_id":403, "quest_module_id":1288, "weight":280},
 {"id":281, "quest_group_id":404, "quest_module_id":1289, "weight":281},
 {"id":282, "quest_group_id":404, "quest_module_id":1290, "weight":282},
 {"id":283, "quest_group_id":404, "quest_module_id":1291, "weight":283},
 {"id":284, "quest_group_id":404, "quest_module_id":1292, "weight":284},
 {"id":285, "quest_group_id":404, "quest_module_id":1293, "weight":285},
 {"id":286, "quest_group_id":404, "quest_module_id":1294, "weight":286},
 {"id":287, "quest_group_id":404, "quest_module_id":1295, "weight":287},
 {"id":288, "quest_group_id":404, "quest_module_id":1296, "weight":288},
 {"id":289, "quest_group_id":404, "quest_module_id":1297, "weight":289},
 {"id":290, "quest_group_id":405, "quest_module_id":1298, "weight":290},
 {"id":291, "quest_group_id":406, "quest_module_id":1299, "weight":291},
 {"id":292, "quest_group_id":406, "quest_module_id":1300, "weight":292},
 {"id":293, "quest_group_id":408, "quest_module_id":1301, "weight":293},
 {"id":294, "quest_group_id":408, "quest_module_id":1302, "weight":294},
 {"id":295, "quest_group_id":408, "quest_module_id":1303, "weight":295},
 {"id":296, "quest_group_id":408, "quest_module_id":1304, "weight":296},
 {"id":297, "quest_group_id":408, "quest_module_id":1305, "weight":297},
 {"id":298, "quest_group_id":408, "quest_module_id":1306, "weight":298},
 {"id":299, "quest_group_id":408, "quest_module_id":1307, "weight":299},
 {"id":300, "quest_group_id":409, "quest_module_id":1308, "weight":300},
 {"id":301, "quest_group_id":409, "quest_module_id":1309, "weight":301},
 {"id":302, "quest_group_id":409, "quest_module_id":1310, "weight":302},
 {"id":303, "quest_group_id":409, "quest_module_id":1311, "weight":303},
 {"id":304, "quest_group_id":409, "quest_module_id":1312, "weight":304},
 {"id":305, "quest_group_id":409, "quest_module_id":1313, "weight":305},
 {"id":306, "quest_group_id":409, "quest_module_id":1314, "weight":306},
 {"id":307, "quest_group_id":410, "quest_module_id":1315, "weight":307},
 {"id":308, "quest_group_id":410, "quest_module_id":1316, "weight":308},
 {"id":309, "quest_group_id":410, "quest_module_id":1317, "weight":309},
 {"id":310, "quest_group_id":410, "quest_module_id":1318, "weight":310},
 {"id":311, "quest_group_id":410, "quest_module_id":1319, "weight":311},
 {"id":312, "quest_group_id":410, "quest_module_id":1320, "weight":312},
 {"id":313, "quest_group_id":410, "quest_module_id":1321, "weight":313},
 {"id":314, "quest_group_id":411, "quest_module_id":1322, "weight":314},
 {"id":315, "quest_group_id":411, "quest_module_id":1323, "weight":315},
 {"id":316, "quest_group_id":411, "quest_module_id":1324, "weight":316},
 {"id":317, "quest_group_id":411, "quest_module_id":1325, "weight":317},
 {"id":318, "quest_group_id":411, "quest_module_id":1326, "weight":318},
 {"id":319, "quest_group_id":412, "quest_module_id":1327, "weight":319},
 {"id":320, "quest_group_id":412, "quest_module_id":1328, "weight":320},
 {"id":321, "quest_group_id":412, "quest_module_id":1329, "weight":321},
 {"id":322, "quest_group_id":412, "quest_module_id":1330, "weight":322},
 {"id":323, "quest_group_id":412, "quest_module_id":1331, "weight":323},
 {"id":324, "quest_group_id":412, "quest_module_id":1332, "weight":324},
 {"id":325, "quest_group_id":412, "quest_module_id":1333, "weight":325},
 {"id":326, "quest_group_id":412, "quest_module_id":1334, "weight":326},
 {"id":327, "quest_group_id":412, "quest_module_id":1335, "weight":327},
 {"id":328, "quest_group_id":412, "quest_module_id":1336, "weight":328},
 {"id":329, "quest_group_id":412, "quest_module_id":1337, "weight":329},
 {"id":330, "quest_group_id":412, "quest_module_id":1338, "weight":330},
 {"id":331, "quest_group_id":412, "quest_module_id":1339, "weight":331},
 {"id":332, "quest_group_id":414, "quest_module_id":1340, "weight":332},
 {"id":333, "quest_group_id":415, "quest_module_id":1341, "weight":333},
 {"id":334, "quest_group_id":415, "quest_module_id":1342, "weight":334},
 {"id":335, "quest_group_id":415, "quest_module_id":1343, "weight":335},
 {"id":336, "quest_group_id":415, "quest_module_id":1344, "weight":336},
 {"id":337, "quest_group_id":415, "quest_module_id":1345, "weight":337},
 {"id":338, "quest_group_id":415, "quest_module_id":1346, "weight":338},
 {"id":339, "quest_group_id":416, "quest_module_id":1347, "weight":339},
 {"id":340, "quest_group_id":416, "quest_module_id":1348, "weight":340},
 {"id":341, "quest_group_id":417, "quest_module_id":1349, "weight":341},
 {"id":342, "quest_group_id":417, "quest_module_id":1350, "weight":342},
 {"id":343, "quest_group_id":417, "quest_module_id":1351, "weight":343},
 {"id":344, "quest_group_id":417, "quest_module_id":1352, "weight":344},
 {"id":345, "quest_group_id":419, "quest_module_id":1353, "weight":345},
 {"id":346, "quest_group_id":420, "quest_module_id":1354, "weight":346},
 {"id":347, "quest_group_id":420, "quest_module_id":1355, "weight":347},
 {"id":348, "quest_group_id":420, "quest_module_id":1356, "weight":348},
 {"id":349, "quest_group_id":420, "quest_module_id":1357, "weight":349},
 {"id":350, "quest_group_id":420, "quest_module_id":1358, "weight":350},
 {"id":351, "quest_group_id":420, "quest_module_id":1359, "weight":351},
 {"id":352, "quest_group_id":420, "quest_module_id":1360, "weight":352},
 {"id":353, "quest_group_id":420, "quest_module_id":1361, "weight":353},
 {"id":354, "quest_group_id":420, "quest_module_id":1362, "weight":354},
 {"id":355, "quest_group_id":420, "quest_module_id":1363, "weight":355},
 {"id":356, "quest_group_id":420, "quest_module_id":1364, "weight":356},
 {"id":357, "quest_group_id":421, "quest_module_id":1365, "weight":357},
 {"id":368, "quest_group_id":424, "quest_module_id":1376, "weight":368},
 {"id":369, "quest_group_id":424, "quest_module_id":1377, "weight":369},
 {"id":370, "quest_group_id":424, "quest_module_id":1378, "weight":370},
 {"id":371, "quest_group_id":424, "quest_module_id":1379, "weight":371},
 {"id":372, "quest_group_id":424, "quest_module_id":1380, "weight":372},
 {"id":373, "quest_group_id":424, "quest_module_id":1381, "weight":373},
 {"id":374, "quest_group_id":424, "quest_module_id":1382, "weight":374},
 {"id":375, "quest_group_id":424, "quest_module_id":1383, "weight":375},
 {"id":376, "quest_group_id":424, "quest_module_id":1384, "weight":376},
 {"id":377, "quest_group_id":424, "quest_module_id":1385, "weight":377},
 {"id":378, "quest_group_id":424, "quest_module_id":1386, "weight":378},
 {"id":379, "quest_group_id":425, "quest_module_id":1387, "weight":379},
 {"id":380, "quest_group_id":425, "quest_module_id":1388, "weight":380},
 {"id":381, "quest_group_id":425, "quest_module_id":1389, "weight":381},
 {"id":382, "quest_group_id":425, "quest_module_id":1390, "weight":382},
 {"id":383, "quest_group_id":425, "quest_module_id":1391, "weight":383},
 {"id":384, "quest_group_id":426, "quest_module_id":1392, "weight":384},
 {"id":385, "quest_group_id":426, "quest_module_id":1393, "weight":385},
 {"id":386, "quest_group_id":426, "quest_module_id":1394, "weight":386},
 {"id":387, "quest_group_id":427, "quest_module_id":1395, "weight":387},
 {"id":388, "quest_group_id":427, "quest_module_id":1396, "weight":388},
 {"id":389, "quest_group_id":427, "quest_module_id":1397, "weight":389},
 {"id":390, "quest_group_id":427, "quest_module_id":1398, "weight":390},
 {"id":391, "quest_group_id":428, "quest_module_id":1399, "weight":391},
 {"id":392, "quest_group_id":428, "quest_module_id":1400, "weight":392},
 {"id":393, "quest_group_id":428, "quest_module_id":1401, "weight":393},
 {"id":394, "quest_group_id":429, "quest_module_id":1402, "weight":394},
 {"id":395, "quest_group_id":429, "quest_module_id":1403, "weight":395},
 {"id":396, "quest_group_id":429, "quest_module_id":1404, "weight":396},
 {"id":397, "quest_group_id":429, "quest_module_id":1405, "weight":397},
 {"id":398, "quest_group_id":430, "quest_module_id":1406, "weight":398},
 {"id":399, "quest_group_id":431, "quest_module_id":1407, "weight":399},
 {"id":400, "quest_group_id":431, "quest_module_id":1408, "weight":400},
 {"id":401, "quest_group_id":432, "quest_module_id":1409, "weight":1},
 {"id":402, "quest_group_id":433, "quest_module_id":1410, "weight":4},
 {"id":403, "quest_group_id":433, "quest_module_id":1411, "weight":1},
 {"id":404, "quest_group_id":433, "quest_module_id":1412, "weight":2},
 {"id":405, "quest_group_id":433, "quest_module_id":1413, "weight":3},
 {"id":406, "quest_group_id":434, "quest_module_id":1414, "weight":406},
 {"id":407, "quest_group_id":437, "quest_module_id":1415, "weight":407},
 {"id":408, "quest_group_id":437, "quest_module_id":1416, "weight":408},
 {"id":409, "quest_group_id":437, "quest_module_id":1417, "weight":409},
 {"id":410, "quest_group_id":438, "quest_module_id":1418, "weight":410},
 {"id":411, "quest_group_id":438, "quest_module_id":1419, "weight":411},
 {"id":412, "quest_group_id":438, "quest_module_id":1420, "weight":412},
 {"id":413, "quest_group_id":438, "quest_module_id":1421, "weight":413},
 {"id":414, "quest_group_id":438, "quest_module_id":1422, "weight":414},
 {"id":415, "quest_group_id":438, "quest_module_id":1423, "weight":415},
 {"id":416, "quest_group_id":438, "quest_module_id":1424, "weight":416},
 {"id":417, "quest_group_id":438, "quest_module_id":1425, "weight":417},
 {"id":418, "quest_group_id":438, "quest_module_id":1426, "weight":418},
 {"id":419, "quest_group_id":439, "quest_module_id":1427, "weight":419},
 {"id":420, "quest_group_id":439, "quest_module_id":1428, "weight":420},
 {"id":421, "quest_group_id":439, "quest_module_id":1429, "weight":421},
 {"id":422, "quest_group_id":439, "quest_module_id":1430, "weight":422},
 {"id":423, "quest_group_id":439, "quest_module_id":1431, "weight":423},
 {"id":424, "quest_group_id":439, "quest_module_id":1432, "weight":424},
 {"id":425, "quest_group_id":439, "quest_module_id":1433, "weight":425},
 {"id":426, "quest_group_id":439, "quest_module_id":1434, "weight":426},
 {"id":427, "quest_group_id":439, "quest_module_id":1435, "weight":427},
 {"id":428, "quest_group_id":439, "quest_module_id":1436, "weight":428},
 {"id":429, "quest_group_id":439, "quest_module_id":1437, "weight":429},
 {"id":430, "quest_group_id":439, "quest_module_id":1438, "weight":430},
 {"id":431, "quest_group_id":439, "quest_module_id":1439, "weight":431},
 {"id":432, "quest_group_id":439, "quest_module_id":1440, "weight":432},
 {"id":433, "quest_group_id":442, "quest_module_id":1441, "weight":433},
 {"id":434, "quest_group_id":442, "quest_module_id":1442, "weight":434},
 {"id":435, "quest_group_id":442, "quest_module_id":1443, "weight":435},
 {"id":436, "quest_group_id":442, "quest_module_id":1444, "weight":436},
 {"id":437, "quest_group_id":442, "quest_module_id":1445, "weight":437},
 {"id":438, "quest_group_id":442, "quest_module_id":1446, "weight":438},
 {"id":439, "quest_group_id":442, "quest_module_id":1447, "weight":439},
 {"id":440, "quest_group_id":442, "quest_module_id":1448, "weight":440},
 {"id":441, "quest_group_id":442, "quest_module_id":1449, "weight":441},
 {"id":442, "quest_group_id":442, "quest_module_id":1450, "weight":442},
 {"id":443, "quest_group_id":442, "quest_module_id":1451, "weight":443},
 {"id":444, "quest_group_id":442, "quest_module_id":1452, "weight":444},
 {"id":445, "quest_group_id":443, "quest_module_id":1453, "weight":445},
 {"id":446, "quest_group_id":443, "quest_module_id":1454, "weight":446},
 {"id":447, "quest_group_id":443, "quest_module_id":1455, "weight":447},
 {"id":448, "quest_group_id":443, "quest_module_id":1456, "weight":448},
 {"id":449, "quest_group_id":443, "quest_module_id":1457, "weight":449},
 {"id":450, "quest_group_id":443, "quest_module_id":1458, "weight":450},
 {"id":451, "quest_group_id":443, "quest_module_id":1459, "weight":451},
 {"id":452, "quest_group_id":443, "quest_module_id":1460, "weight":452},
 {"id":453, "quest_group_id":443, "quest_module_id":1461, "weight":453},
 {"id":454, "quest_group_id":443, "quest_module_id":1462, "weight":454},
 {"id":455, "quest_group_id":444, "quest_module_id":1463, "weight":455},
 {"id":456, "quest_group_id":444, "quest_module_id":1464, "weight":456},
 {"id":457, "quest_group_id":444, "quest_module_id":1465, "weight":457},
 {"id":458, "quest_group_id":444, "quest_module_id":1466, "weight":458},
 {"id":459, "quest_group_id":444, "quest_module_id":1467, "weight":459},
 {"id":460, "quest_group_id":444, "quest_module_id":1468, "weight":460},
 {"id":461, "quest_group_id":444, "quest_module_id":1469, "weight":461},
 {"id":462, "quest_group_id":444, "quest_module_id":1470, "weight":462},
 {"id":463, "quest_group_id":444, "quest_module_id":1471, "weight":463},
 {"id":464, "quest_group_id":446, "quest_module_id":1472, "weight":464},
 {"id":465, "quest_group_id":446, "quest_module_id":1473, "weight":465},
 {"id":466, "quest_group_id":446, "quest_module_id":1474, "weight":466},
 {"id":467, "quest_group_id":446, "quest_module_id":1475, "weight":467},
 {"id":468, "quest_group_id":446, "quest_module_id":1476, "weight":468},
 {"id":469, "quest_group_id":447, "quest_module_id":1477, "weight":469},
 {"id":470, "quest_group_id":447, "quest_module_id":1478, "weight":470},
 {"id":471, "quest_group_id":447, "quest_module_id":1479, "weight":471},
 {"id":472, "quest_group_id":447, "quest_module_id":1480, "weight":472},
 {"id":473, "quest_group_id":447, "quest_module_id":1481, "weight":473},
 {"id":474, "quest_group_id":449, "quest_module_id":1482, "weight":474},
 {"id":475, "quest_group_id":449, "quest_module_id":1483, "weight":475},
 {"id":476, "quest_group_id":449, "quest_module_id":1484, "weight":476},
 {"id":477, "quest_group_id":449, "quest_module_id":1485, "weight":477},
 {"id":478, "quest_group_id":449, "quest_module_id":1486, "weight":478},
 {"id":479, "quest_group_id":449, "quest_module_id":1487, "weight":479},
 {"id":480, "quest_group_id":449, "quest_module_id":1488, "weight":480},
 {"id":481, "quest_group_id":450, "quest_module_id":1489, "weight":481},
 {"id":482, "quest_group_id":450, "quest_module_id":1490, "weight":482},
 {"id":483, "quest_group_id":450, "quest_module_id":1491, "weight":483},
 {"id":484, "quest_group_id":450, "quest_module_id":1492, "weight":484},
 {"id":485, "quest_group_id":450, "quest_module_id":1493, "weight":485},
 {"id":486, "quest_group_id":450, "quest_module_id":1494, "weight":486},
 {"id":487, "quest_group_id":450, "quest_module_id":1495, "weight":487},
 {"id":488, "quest_group_id":451, "quest_module_id":1496, "weight":488},
 {"id":489, "quest_group_id":451, "quest_module_id":1497, "weight":489},
 {"id":490, "quest_group_id":451, "quest_module_id":1498, "weight":490},
 {"id":491, "quest_group_id":451, "quest_module_id":1499, "weight":491},
 {"id":492, "quest_group_id":453, "quest_module_id":1500, "weight":492},
 {"id":493, "quest_group_id":454, "quest_module_id":1501, "weight":493},
 {"id":494, "quest_group_id":454, "quest_module_id":1502, "weight":494},
 {"id":495, "quest_group_id":454, "quest_module_id":1503, "weight":495},
 {"id":496, "quest_group_id":455, "quest_module_id":1504, "weight":496},
 {"id":497, "quest_group_id":455, "quest_module_id":1505, "weight":497},
 {"id":498, "quest_group_id":455, "quest_module_id":1506, "weight":498},
 {"id":499, "quest_group_id":455, "quest_module_id":1507, "weight":499},
 {"id":500, "quest_group_id":455, "quest_module_id":1508, "weight":500},
 {"id":501, "quest_group_id":455, "quest_module_id":1509, "weight":501},
 {"id":502, "quest_group_id":455, "quest_module_id":1510, "weight":502},
 {"id":503, "quest_group_id":455, "quest_module_id":1511, "weight":503},
 {"id":504, "quest_group_id":456, "quest_module_id":1512, "weight":504},
 {"id":506, "quest_group_id":356, "quest_module_id":1514, "weight":2},
 {"id":508, "quest_group_id":356, "quest_module_id":1516, "weight":3},
 {"id":509, "quest_group_id":356, "quest_module_id":1518, "weight":4},
 {"id":510, "quest_group_id":356, "quest_module_id":1519, "weight":5},
 {"id":511, "quest_group_id":356, "quest_module_id":1520, "weight":6},
 {"id":512, "quest_group_id":356, "quest_module_id":1521, "weight":7},
 {"id":513, "quest_group_id":356, "quest_module_id":1522, "weight":8},
 {"id":514, "quest_group_id":356, "quest_module_id":1523, "weight":9},
 {"id":515, "quest_group_id":356, "quest_module_id":1524, "weight":10},
 {"id":516, "quest_group_id":356, "quest_module_id":1525, "weight":11},
 {"id":517, "quest_group_id":356, "quest_module_id":1526, "weight":12},
 {"id":518, "quest_group_id":356, "quest_module_id":1527, "weight":13},
 {"id":519, "quest_group_id":369, "quest_module_id":1528, "weight":1},
 {"id":520, "quest_group_id":369, "quest_module_id":1529, "weight":2},
 {"id":521, "quest_group_id":369, "quest_module_id":1530, "weight":3},
 {"id":522, "quest_group_id":369, "quest_module_id":1531, "weight":4},
 {"id":523, "quest_group_id":369, "quest_module_id":1532, "weight":5},
 {"id":524, "quest_group_id":369, "quest_module_id":1533, "weight":6},
 {"id":525, "quest_group_id":369, "quest_module_id":1534, "weight":7},
 {"id":526, "quest_group_id":369, "quest_module_id":1535, "weight":8},
 {"id":527, "quest_group_id":369, "quest_module_id":1536, "weight":9},
 {"id":528, "quest_group_id":370, "quest_module_id":1537, "weight":1},
 {"id":529, "quest_group_id":370, "quest_module_id":1538, "weight":2},
 {"id":530, "quest_group_id":370, "quest_module_id":1539, "weight":3},
 {"id":531, "quest_group_id":370, "quest_module_id":1540, "weight":4},
 {"id":532, "quest_group_id":389, "quest_module_id":1541, "weight":2},
 {"id":533, "quest_group_id":389, "quest_module_id":1542, "weight":3},
 {"id":561, "quest_group_id":432, "quest_module_id":1570, "weight":2},
 {"id":562, "quest_group_id":432, "quest_module_id":1571, "weight":2},
 {"id":563, "quest_group_id":432, "quest_module_id":1572, "weight":2},
 {"id":566, "quest_group_id":468, "quest_module_id":1575, "weight":3},
 {"id":567, "quest_group_id":468, "quest_module_id":1576, "weight":4},
 {"id":568, "quest_group_id":468, "quest_module_id":1577, "weight":5},
 {"id":569, "quest_group_id":468, "quest_module_id":1578, "weight":6},
 {"id":570, "quest_group_id":444, "quest_module_id":1580, "weight":0},
 {"id":571, "quest_group_id":468, "quest_module_id":1582, "weight":0},
 {"id":572, "quest_group_id":468, "quest_module_id":1583, "weight":1},
 {"id":573, "quest_group_id":468, "quest_module_id":1584, "weight":2},
 {"id":574, "quest_group_id":468, "quest_module_id":1585, "weight":7},
 {"id":575, "quest_group_id":468, "quest_module_id":1586, "weight":8},
 {"id":577, "quest_group_id":468, "quest_module_id":1588, "weight":9},
 {"id":578, "quest_group_id":468, "quest_module_id":1589, "weight":10},
 {"id":579, "quest_group_id":468, "quest_module_id":1590, "weight":11},
 {"id":586, "quest_group_id":471, "quest_module_id":1597, "weight":0},
 {"id":587, "quest_group_id":471, "quest_module_id":1598, "weight":1},
 {"id":588, "quest_group_id":471, "quest_module_id":1599, "weight":2},
 {"id":589, "quest_group_id":471, "quest_module_id":1600, "weight":3}]